tests/__init__.py
tests/test_calc.py
tests/test_lonlat.py
tests/test_transform.py
tests/test_utils.py
to4326/__init__.py
to4326/calc.py
to4326/constants.py
to4326/exceptions.py
to4326/lonlat.py
to4326/transform.py
to4326/types.py
to4326/utils.py
to4326/validate.py
to4326-1.0.3.dist-info/LICENSE
to4326-1.0.3.dist-info/METADATA
to4326-1.0.3.dist-info/WHEEL
to4326-1.0.3.dist-info/top_level.txt
to4326-1.0.3.dist-info/RECORD
