Metadata-Version: 2.1
Name: to4326
Version: 1.0.3
Summary: UNKNOWN
Home-page: https://github.com/yonda-yonda/to4326
Author: yonda
Author-email: yonda.fountain@gmail.com
License: UNKNOWN
Platform: UNKNOWN
Classifier: License :: OSI Approved :: MIT License
Classifier: Programming Language :: Python :: 3
Classifier: Topic :: Scientific/Engineering :: GIS
Requires-Python: >=3.7
Requires-Dist: pyproj (>=3.0.0)
